siteforge/__init__.py
siteforge/applications.py
siteforge/background.py
siteforge/convertors.py
siteforge/datastructures.py
siteforge/exceptions.py
siteforge/py.typed
siteforge/requests.py
siteforge/responses.py
siteforge/routing.py
siteforge/staticfiles.py
siteforge/templating.py
siteforge/websockets.py
siteforge/middleware/__init__.py
siteforge/middleware/cors.py
siteforge/middleware/errors.py
siteforge/middleware/exceptions.py
siteforge/middleware/gzip.py
siteforge/middleware/httpsredirect.py
siteforge/middleware/sessions.py
siteforge/middleware/trustedhost.py
siteforge/tests/__init__.py
siteforge/tests/conftest.py
siteforge/tests/test_applications.py
siteforge/tests/test_background.py
siteforge/tests/test_concurrency.py
siteforge/tests/test_convertors.py
siteforge/tests/test_datastructures.py
siteforge/tests/test_exceptions.py
siteforge/tests/test_formparsers.py
siteforge/tests/test_requests.py
siteforge/tests/test_responses.py
siteforge/tests/test_routing.py
siteforge/tests/test_staticfiles.py
siteforge/tests/test_status.py
siteforge/tests/test_templates.py
siteforge/tests/test_websockets.py
siteforge/tests/types.py
siteforge/tests/middleware/__init__.py
siteforge/tests/middleware/test_cors.py
siteforge/tests/middleware/test_errors.py
siteforge/tests/middleware/test_gzip.py
siteforge/tests/middleware/test_https_redirect.py
siteforge/tests/middleware/test_middleware.py
siteforge/tests/middleware/test_session.py
siteforge/tests/middleware/test_trusted_host.py
siteforge/tests/middleware/test_wsgi.py
siteforge/tests/statics/example.txt
siteforge-0.0.11.dist-info/METADATA
siteforge-0.0.11.dist-info/WHEEL
siteforge-0.0.11.dist-info/RECORD
